dis_cli.py
dis_cli-0.3.0.dist-info/LICENSE
dis_cli-0.3.0.dist-info/METADATA
dis_cli-0.3.0.dist-info/WHEEL
dis_cli-0.3.0.dist-info/entry_points.txt
dis_cli-0.3.0.dist-info/top_level.txt
dis_cli-0.3.0.dist-info/RECORD
