Metadata-Version: 2.1
Name: dis-cli
Version: 0.3.0
Summary: A tool to inspect disassembled Python code on the command line.
Home-page: https://github.com/JoshKarpel/dis-cli
Author: Josh Karpel
Author-email: josh.karpel@gmail.com
License: MIT
Platform: UNKNOWN
Classifier: Development Status :: 3 - Alpha
Classifier: Environment :: Console
Classifier: Intended Audience :: Developers
Classifier: Intended Audience :: Education
Classifier: License :: OSI Approved :: MIT License
Classifier: Operating System :: OS Independent
Classifier: Programming Language :: Python :: 3
Classifier: Programming Language :: Python :: 3 :: Only
Classifier: Programming Language :: Python :: 3.7
Classifier: Programming Language :: Python :: 3.8
Classifier: Programming Language :: Python :: 3.9
Classifier: Programming Language :: Python :: 3.10
Classifier: Topic :: Software Development
Classifier: Topic :: Software Development :: Disassemblers
Classifier: Topic :: Utilities
Requires-Python: >=3.7
License-File: LICENSE
Requires-Dist: click (>=8)
Requires-Dist: rich (>=12)
Provides-Extra: tests
Requires-Dist: mypy (>=0.942) ; extra == 'tests'
Requires-Dist: pytest (>=7.1) ; extra == 'tests'
Requires-Dist: pytest-cov (>=3) ; extra == 'tests'
Requires-Dist: pytest-mypy (>=0.9) ; extra == 'tests'
Requires-Dist: types-click (>=7) ; extra == 'tests'
Requires-Dist: importlib-metadata ; (python_version < "3.8") and extra == 'tests'
